.coveragerc
.mailmap
.testr.conf
AUTHORS
CONTRIBUTING.rst
ChangeLog
HACKING.rst
LICENSE
MANIFEST.in
README.rst
babel.cfg
requirements.txt
setup.cfg
setup.py
test-requirements.txt
tox.ini
doc/source/conf.py
doc/source/contributing.rst
doc/source/index.rst
doc/source/installation.rst
doc/source/readme.rst
doc/source/usage.rst
openstacksdk_plugin/__init__.py
openstacksdk_plugin/shell.py
openstacksdk_plugin/vendor.py
openstacksdk_plugin.egg-info/PKG-INFO
openstacksdk_plugin.egg-info/SOURCES.txt
openstacksdk_plugin.egg-info/dependency_links.txt
openstacksdk_plugin.egg-info/entry_points.txt
openstacksdk_plugin.egg-info/not-zip-safe
openstacksdk_plugin.egg-info/pbr.json
openstacksdk_plugin.egg-info/requires.txt
openstacksdk_plugin.egg-info/test-requires.txt
openstacksdk_plugin.egg-info/top_level.txt
openstacksdk_plugin/example/__init__.py
openstacksdk_plugin/example/example_service.py
openstacksdk_plugin/example/v1/__init__.py
openstacksdk_plugin/example/v1/_proxy.py
openstacksdk_plugin/other/__init__.py
openstacksdk_plugin/other/other_service.py
openstacksdk_plugin/other/v1/__init__.py
openstacksdk_plugin/other/v1/_proxy.py
openstacksdk_plugin/tests/__init__.py
openstacksdk_plugin/tests/functional/__init__.py
openstacksdk_plugin/tests/unit/__init__.py
openstacksdk_plugin/tests/unit/example/__init__.py
openstacksdk_plugin/tests/unit/example/test_example_service.py
openstacksdk_plugin/tests/unit/example/v1/__init__.py
openstacksdk_plugin/tests/unit/example/v1/test_proxy.py
openstacksdk_plugin/tests/unit/other/__init__.py
openstacksdk_plugin/tests/unit/other/test_other_service.py
openstacksdk_plugin/tests/unit/other/v1/__init__.py
openstacksdk_plugin/tests/unit/other/v1/test_proxy.py